pybottrain/__init__.py
pybottrain/advanced.py
pybottrain/bot.py
pybottrain/loop.py
pybottrain-1.0.6.dist-info/METADATA
pybottrain-1.0.6.dist-info/WHEEL
pybottrain-1.0.6.dist-info/top_level.txt
pybottrain-1.0.6.dist-info/RECORD
