Metadata-Version: 2.1
Name: pybottrain
Version: 1.0.6
Summary: python bot creator library
Home-page: UNKNOWN
Author: icarogamer2001
Author-email: deiamota050@gmail.com
License: UNKNOWN
Platform: UNKNOWN
Requires-Python: >=3.6
